ak_androguard-3.3.7.data/scripts/androarsc.py
ak_androguard-3.3.7.data/scripts/androauto.py
ak_androguard-3.3.7.data/scripts/androaxml.py
ak_androguard-3.3.7.data/scripts/androcg.py
ak_androguard-3.3.7.data/scripts/androdd.py
ak_androguard-3.3.7.data/scripts/androdis.py
ak_androguard-3.3.7.data/scripts/androgui.py
ak_androguard-3.3.7.data/scripts/androlyze.py
ak_androguard-3.3.7.data/scripts/androsign.py
ak_androguard-3.3.7.dist-info/METADATA
ak_androguard-3.3.7.dist-info/RECORD
ak_androguard-3.3.7.dist-info/WHEEL
ak_androguard-3.3.7.dist-info/top_level.txt
androguard/__init__.py
androguard/misc.py
androguard/session.py
androguard/util.py
androguard/core/__init__.py
androguard/core/androconf.py
androguard/core/bytecode.py
androguard/core/analysis/__init__.py
androguard/core/analysis/analysis.py
androguard/core/analysis/auto.py
androguard/core/analysis/tags.py
androguard/core/api_specific_resources/__init__.py
androguard/core/api_specific_resources/aosp_permissions/__init__.py
androguard/core/api_specific_resources/aosp_permissions/aosp_permissions.py
androguard/core/api_specific_resources/aosp_permissions/aosp_permissions_api10.py
androguard/core/api_specific_resources/aosp_permissions/aosp_permissions_api14.py
androguard/core/api_specific_resources/aosp_permissions/aosp_permissions_api15.py
androguard/core/api_specific_resources/aosp_permissions/aosp_permissions_api16.py
androguard/core/api_specific_resources/aosp_permissions/aosp_permissions_api17.py
androguard/core/api_specific_resources/aosp_permissions/aosp_permissions_api18.py
androguard/core/api_specific_resources/aosp_permissions/aosp_permissions_api19.py
androguard/core/api_specific_resources/aosp_permissions/aosp_permissions_api21.py
androguard/core/api_specific_resources/aosp_permissions/aosp_permissions_api22.py
androguard/core/api_specific_resources/aosp_permissions/aosp_permissions_api9.py
androguard/core/api_specific_resources/aosp_permissions/permissions_16.json
androguard/core/api_specific_resources/aosp_permissions/permissions_17.json
androguard/core/api_specific_resources/aosp_permissions/permissions_18.json
