Metadata-Version: 2.1
Name: ak-androguard
Version: 3.3.7
Summary: A fork of official Androguard project. Androguard is a full python tool to play with Android files.
Home-page: https://github.com/androguard/androguard
License: Apache Licence, Version 2.0
Download-URL: https://github.com/androguard/androguard/releases
Platform: UNKNOWN
Provides-Extra: GUI
Provides-Extra: docs
Provides-Extra: magic
Provides-Extra: tests
Provides-Extra: graphing
Requires-Dist: future
Requires-Dist: networkx (>=1.11)
Requires-Dist: pygments
Requires-Dist: lxml
Requires-Dist: colorama
Requires-Dist: matplotlib
Requires-Dist: asn1crypto (>=0.24.0)
Requires-Dist: ipython (>=5.0.0)
Provides-Extra: GUI
Requires-Dist: pyperclip; extra == 'GUI'
Requires-Dist: PyQt5; extra == 'GUI'
Provides-Extra: docs
Requires-Dist: sphinx; extra == 'docs'
Requires-Dist: sphinxcontrib-programoutput (>0.8); extra == 'docs'
Requires-Dist: sphinx-rtd-theme; extra == 'docs'
Provides-Extra: graphing
Requires-Dist: pydot; extra == 'graphing'
Provides-Extra: magic
Requires-Dist: file-magic; extra == 'magic'
Provides-Extra: tests
Requires-Dist: mock (>=2.0); extra == 'tests'
Requires-Dist: nose; extra == 'tests'
Requires-Dist: codecov; extra == 'tests'
Requires-Dist: coverage; extra == 'tests'
Requires-Dist: nose-timer; extra == 'tests'
